arraytool/__init__.py
arraytool/core.py
arraytool/decorator.py
arraytool/pytool.py
arraytool-0.1.5.dist-info/LICENSE
arraytool-0.1.5.dist-info/METADATA
arraytool-0.1.5.dist-info/WHEEL
arraytool-0.1.5.dist-info/top_level.txt
arraytool-0.1.5.dist-info/RECORD
