Metadata-Version: 2.1
Name: arraytool
Version: 0.1.5
Summary: 基于numpy的Series及DataFrame数据结构
Home-page: https://gitee.com/yonder_sky/arraytool
Author: 春秋迭代
Author-email: yondersky@126.com
License: UNKNOWN
Platform: UNKNOWN
Classifier: Programming Language :: Python :: 3
Classifier: License :: OSI Approved :: BSD License
Classifier: Operating System :: OS Independent
License-File: LICENSE
